<?xml version="1.0" encoding="utf-8"?>
<LanguageData>
  <!--The following translations were generated by https://www.deepl.com/-->
  <!-- EN: bismuth bronze tile -->
  <CAL_BismuthBronzeTile.label>Wismut Bronze Fliese</CAL_BismuthBronzeTile.label>
  <!-- EN: Bismuth bronze tiles, for a neutral look. -->
  <CAL_BismuthBronzeTile.description>Bismut-Bronze-Fliesen, für ein neutrales Aussehen.</CAL_BismuthBronzeTile.description>
  <!-- EN: bronze tile -->
  <CAL_BronzeTile.label>Bronzefliese</CAL_BronzeTile.label>
  <!-- EN: Bronze tiles, for a neutral look. -->
  <CAL_BronzeTile.description>Bronze-Kacheln, für ein neutrales Aussehen.</CAL_BronzeTile.description>
  <!-- EN: cupronickel tile -->
  <CAL_CupronickelTile.label>Cupronickel-Kachel</CAL_CupronickelTile.label>
  <!-- EN: Cupronickel tiles, for a utilitarian look. -->
  <CAL_CupronickelTile.description>Cupronickel-Fliesen, für einen utilitaristischen Look.</CAL_CupronickelTile.description>
  <!-- EN: duralumin tile -->
  <CAL_DuraluminTile.label>Duralumin-Platte</CAL_DuraluminTile.label>
  <!-- EN: Duralumin tiles, for a light and clean look. -->
  <CAL_DuraluminTile.description>Duralumin Kacheln, für ein helles und sauberes Aussehen.</CAL_DuraluminTile.description>
  <!-- EN: hepatzion tile -->
  <CAL_HepatzionTile.label>Hepatzion-Kachel</CAL_HepatzionTile.label>
  <!-- EN: Hepatzion tiles, for a dark and clean look. Pretty, but labor-intensive. -->
  <CAL_HepatzionTile.description>Hepatzion-Kacheln, für ein dunkles und sauberes Aussehen. Hübsch, aber arbeitsintensiv.</CAL_HepatzionTile.description>
  <!-- EN: plumchalcum tile -->
  <CAL_PlumchalcumTile.label>Plumchalcum-Kachel</CAL_PlumchalcumTile.label>
  <!-- EN: Plumchalcum tiles, for a dark look. Quick to build. -->
  <CAL_PlumchalcumTile.description>Plumchalcum-Kacheln, für ein dunkles Aussehen. Schnell zu bauen.</CAL_PlumchalcumTile.description>
  <!-- EN: stainless steel tile -->
  <CAL_StainlessSteelTile.label>Kachel aus rostfreiem Stahl</CAL_StainlessSteelTile.label>
  <!-- EN: Stainless steel tiles, for keeping rooms clean. Neutral in terms of looks and very slow to build. -->
  <CAL_StainlessSteelTile.description>Kacheln aus rostfreiem Stahl, um Räume sauber zu halten. Neutral in Bezug auf das Aussehen und sehr langsam zu bauen.</CAL_StainlessSteelTile.description>
  <!-- EN: zamak tile -->
  <CAL_ZamakTile.label>Zamak-Kachel</CAL_ZamakTile.label>
  <!-- EN: Zamak tiles, for a utilitarian look. -->
  <CAL_ZamakTile.description>Zamak Kacheln, für einen utilitaristischen Look.</CAL_ZamakTile.description>
</LanguageData>
